[{"filename":"travel-in-beijing","md":"","html":"","metadata":{"title":"Travel in Beijing","created":"2019-07-23","updated":"2019-07-23","category":"Blog","tags":["Trips"],"cover":"https://img.aquariuslt.com/posts/2019/07/palace-museum-01.jpg"},"summary":"毕业第四年后，终于有机会第一次旅行，目的地选择了北京。本次北京行采用的是语文课本童年回忆随缘踩点法，在打卡景点的同时，顺便会一下闻名已久的北京帮朋友。算上两天年假，一共有四天假期，周四晚上飞机，周一晚","toc":[{"label":"Travel in Beijing","level":1,"id":"travel-in-beijing","position":0,"children":[{"label":"Day0: 凌晨四点中关村之旅","level":2,"id":"day0-凌晨四点中关村之旅","position":1,"children":[],"pid":0},{"label":"Day1: 国家奥体中心","level":2,"id":"day1-国家奥体中心","position":2,"children":[],"pid":0},{"label":"Day2: 故宫博物馆线","level":2,"id":"day2-故宫博物馆线","position":3,"children":[],"pid":0},{"label":"Day3: 烈日攀爬长城","level":2,"id":"day3-烈日攀爬长城","position":4,"children":[],"pid":0},{"label":"Day4: 清北潜入作战","level":2,"id":"day4-清北潜入作战","position":5,"children":[],"pid":0},{"label":"北京印象","level":2,"id":"北京印象","position":6,"children":[{"label":"食","level":3,"id":"食","position":7,"children":[],"pid":6},{"label":"行","level":3,"id":"行","position":8,"children":[],"pid":6},{"label":"住","level":3,"id":"住","position":9,"children":[],"pid":6}],"pid":0}],"pid":-1}],"images":["https://img.aquariuslt.com/posts/2019/07/msra.png","https://img.aquariuslt.com/posts/2019/07/bird-nest.png","https://img.aquariuslt.com/posts/2019/07/bird-nest-show.jpg","https://img.aquariuslt.com/posts/2019/07/water-m3.png","https://img.aquariuslt.com/posts/2019/07/palace-museum-01.jpg","https://img.aquariuslt.com/posts/2019/07/palace-museum-02.png","https://img.aquariuslt.com/posts/2019/07/palace-museum-03.png","https://img.aquariuslt.com/posts/2019/07/palace-museum-04.jpg","https://img.aquariuslt.com/posts/2019/07/palace-museum-05.jpg","https://img.aquariuslt.com/posts/2019/07/great-wall-01.jpg","https://img.aquariuslt.com/posts/2019/07/great-wall-02.jpg","https://img.aquariuslt.com/posts/2019/07/great-wall-03.jpg","https://img.aquariuslt.com/posts/2019/07/pku-untitled-lake.jpg"],"opengraph":{"og:title":"Travel in Beijing","og:type":"article","og:image":"https://img.aquariuslt.com/posts/2019/07/palace-museum-01.jpg","og:url":"https://blog.aquariuslt.com/posts/2019/07/23/travel-in-beijing","og:description":"毕业第四年后，终于有机会第一次旅行，目的地选择了北京。本次北京行采用的是语文课本童年回忆随缘踩点法，在打卡景点的同时，顺便会一下闻名已久的北京帮朋友。算上两天年假，一共有四天假期，周四晚上飞机，周一晚","article:author":"Aquariuslt","article:section":"Blog","article:tag":"Trips","article:published_time":"2019-07-23","article:modified_time":"2019-07-23","website":"https://blog.aquariuslt.com"},"jsonld":{"@type":"Article","articleBody":"毕业第四年后，终于有机会第一次旅行，目的地选择了北京。本次北京行采用的是语文课本童年回忆随缘踩点法，在打卡景点的同时，顺便会一下闻名已久的北京帮朋友。算上两天年假，一共有四天假期，周四晚上飞机，周一晚","articleSection":["Travel in Beijing"],"wordCount":2782,"author":{"@type":"Person","image":"https://avatars2.githubusercontent.com/u/6554061?s=460&v=4","name":"Aquariuslt","url":"blog.aquariuslt.com","identifier":"Aquariuslt","description":"Personal Blog | Coder | WoWer | On the way.","mainEntityOfPage":"Personal Blog | Coder | WoWer | On the way."},"keywords":["Trips"],"thumbnailUrl":"https://img.aquariuslt.com/posts/2019/07/palace-museum-01.jpg","version":"2019-07-23","text":"毕业第四年后，终于有机会第一次旅行，目的地选择了北京。本次北京行采用的是语文课本童年回忆随缘踩点法，在打卡景点的同时，顺便会一下闻名已久的北京帮朋友。算上两天年假，一共有四天假期，周四晚上飞机，周一晚"},"permalink":"/2019/07/23/travel-in-beijing"}]