[{"filename":"nodejs-oracledb-install-on-rhel-6","md":"","html":"","metadata":{"title":"RHEL(CentOS)6环境下安装node-oracledb","created":"2016-01-11","updated":"2016-01-11","category":"Debug","tags":["Node","Linux"],"cover":"https://picsum.photos/id/306/800/300"},"summary":"最近准备升级一下 PROD 服务器上的`node-oracledb`版本. 但是遇到一个很奇怪的现象,就是我本地无法构建出服务器上可用的`oracledb`. (因为部署方式是打包部署而不是从`git","toc":[{"label":"RHEL(CentOS)6 环境下安装 node-oracledb","level":1,"id":"rhelcentos6-环境下安装-node-oracledb","position":0,"children":[{"label":"Background","level":2,"id":"background","position":1,"children":[],"pid":0},{"label":"RootCause","level":2,"id":"rootcause","position":2,"children":[],"pid":0},{"label":"Solution","level":2,"id":"solution","position":3,"children":[],"pid":0}],"pid":-1}],"images":[],"opengraph":{"og:title":"RHEL(CentOS)6环境下安装node-oracledb","og:type":"article","og:image":"https://picsum.photos/id/306/800/300","og:url":"https://blog.aquariuslt.com/posts/2016/01/11/nodejs-oracledb-install-on-rhel-6","og:description":"最近准备升级一下 PROD 服务器上的`node-oracledb`版本. 但是遇到一个很奇怪的现象,就是我本地无法构建出服务器上可用的`oracledb`. (因为部署方式是打包部署而不是从`git","article:author":"Aquariuslt","article:section":"Debug","article:tag":"Node,Linux","article:published_time":"2016-01-11","article:modified_time":"2016-01-11","website":"https://blog.aquariuslt.com"},"jsonld":{"@type":"Article","articleBody":"最近准备升级一下 PROD 服务器上的`node-oracledb`版本. 但是遇到一个很奇怪的现象,就是我本地无法构建出服务器上可用的`oracledb`. (因为部署方式是打包部署而不是从`git","articleSection":["RHEL(CentOS)6 环境下安装 node-oracledb"],"wordCount":1246,"author":{"@type":"Person","image":"https://avatars2.githubusercontent.com/u/6554061?s=460&v=4","name":"Aquariuslt","url":"blog.aquariuslt.com","identifier":"Aquariuslt","description":"Personal Blog | Coder | WoWer | On the way.","mainEntityOfPage":"Personal Blog | Coder | WoWer | On the way."},"keywords":["Node","Linux"],"thumbnailUrl":"https://picsum.photos/id/306/800/300","version":"2016-01-11","text":"最近准备升级一下 PROD 服务器上的`node-oracledb`版本. 但是遇到一个很奇怪的现象,就是我本地无法构建出服务器上可用的`oracledb`. (因为部署方式是打包部署而不是从`git"},"permalink":"/2016/01/11/nodejs-oracledb-install-on-rhel-6"}]